pyqms/__init__.py
pyqms/adaptors.py
pyqms/isotopologue_library.py
pyqms/knowledge_base.py
pyqms/params.py
pyqms/results.py
pyqms/version.txt
pyqms/kb/ext/unimod.xml
pyqms-0.6.5.dist-info/LICENSE
pyqms-0.6.5.dist-info/METADATA
pyqms-0.6.5.dist-info/WHEEL
pyqms-0.6.5.dist-info/top_level.txt
pyqms-0.6.5.dist-info/RECORD
