Metadata-Version: 2.1
Name: pyqms
Version: 0.6.5
Summary: pyQms - Python module for accurate quantification of mass spectrometry data
Home-page: https://github.com/pyQms/pyqms
Author: Johannes Leufken, Anna Niehues, L. Peter Sarin, Florian Wessels, Michael Hippler, Sebastian A. Leidel and Christian Fufezan
Author-email: christian@fufezan.net
License: The MIT License (MIT)
Platform: any that supports python 3.4
Classifier: Development Status :: 4 - Beta
Classifier: Environment :: Console
Classifier: Intended Audience :: Education
Classifier: Intended Audience :: Science/Research
Classifier: Intended Audience :: Developers
Classifier: Operating System :: MacOS :: MacOS X
Classifier: Operating System :: Microsoft :: Windows
Classifier: Operating System :: POSIX
Classifier: Operating System :: POSIX :: SunOS/Solaris
Classifier: Operating System :: Unix
Classifier: Programming Language :: Python :: 3
Classifier: Programming Language :: Python :: 3.5
Classifier: Topic :: Scientific/Engineering :: Astronomy
Classifier: Topic :: Scientific/Engineering :: Atmospheric Science
Classifier: Topic :: Scientific/Engineering :: Bio-Informatics
Classifier: Topic :: Scientific/Engineering :: Chemistry
Classifier: Topic :: Scientific/Engineering :: Information Analysis
Classifier: Topic :: Scientific/Engineering :: Medical Science Apps.
Classifier: Topic :: Scientific/Engineering :: Physics
License-File: LICENSE
Requires-Dist: pymzml
Requires-Dist: openpyxl
Requires-Dist: chemical-composition
